{
  "code": 0,
  "data": {
    "routers": [
      {
        "id": 4637,
        "CreatedAt": "2023-03-19T23:17:17.853+08:00",
        "UpdatedAt": "2023-03-19T23:17:17.853+08:00",
        "parent_id": 0,
        "path": "",
        "name": "报警",
        "hidden": 2,

        "sort": 1,
        "meta": {
          "type": "M",
          "redirect": "",
          "icon": "IconBytedanceColor",
          "activeName": "",
          "keepAlive": false,
          "defaultMenu": false,
          "title": "报警",
          "closeTab": false
        },
        "authoritys": null,
        "menuBtn": null,
        "level": "",
        "code": "online",
        "route": "online",
        "redirect": null,
        "status": 1,
        "remark": null,
        "menuId": 4637,
        "children": [
          {
            "id": 4638,
            "CreatedAt": "2023-03-19T23:18:43.918+08:00",
            "UpdatedAt": "2023-03-19T23:18:43.918+08:00",
            "parent_id": 4637,
            "path": "/alerts",
            "name": "报警",
            "hidden": 2,
            "component": "alerts/index",
            "sort": 1,
            "meta": {
              "type": "M",
              "redirect": "",
              "icon": "IconRobot",
              "activeName": "",
              "keepAlive": false,
              "defaultMenu": false,
              "title": "报警",
              "closeTab": false
            },
            "authoritys": null,
            "menuBtn": null,
            "level": "",
            "code": "bots",

            "redirect": null,
            "status": 1,
            "remark": null,
            "menuId": 4638,
            "children": null,
            "parameters": [],
            "btns": null
          },
          {
            "id": 4639,
            "CreatedAt": "2023-03-19T23:20:24.564+08:00",
            "UpdatedAt": "2023-03-21T12:33:06.682+08:00",
            "parent_id": 4637,
            "path": "/notify",
            "name": "报警列表",
            "hidden": 2,
            "component": "notify/index",
            "sort": 1,
            "meta": {
              "type": "M",
              "redirect": "",
              "icon": "IconUserGroup",
              "activeName": "",
              "keepAlive": false,
              "defaultMenu": false,
              "title": "报警列表",
              "closeTab": false
            },
            "authoritys": null,
            "menuBtn": null,
            "level": "",
            "code": "bots:exchange",
            "route": "/bots/exchange",
            "redirect": null,
            "status": 1,
            "remark": null,
            "menuId": 4639,
            "children": null,
            "parameters": [],
            "btns": null
          }
        ],
        "parameters": [],
        "btns": null
      },
      {
        "id": 4606,
        "CreatedAt": "2023-03-19T17:37:36.939+08:00",
        "UpdatedAt": "2023-03-19T19:37:59.778+08:00",
        "parent_id": 0,
        "path": "/strategies",
        "name": "策略",
        "hidden": 2,
        "component": "",
        "sort": 1,
        "meta": {
          "type": "M",
          "redirect": "",
          "icon": "IconCodeSquare",
          "activeName": "",
          "keepAlive": false,
          "defaultMenu": false,
          "title": "策略",
          "closeTab": false
        },
        "authoritys": null,
        "menuBtn": null,
        "level": "",
        "code": "strategies",
        "route": "/strategies",
        "redirect": null,
        "status": 1,
        "remark": null,
        "menuId": 4606,
        "children": [
          {
            "id": 4604,
            "CreatedAt": "2023-03-19T16:15:15.758+08:00",
            "UpdatedAt": "2023-03-19T19:38:17.663+08:00",
            "parent_id": 4606,
            "path": "strategies/code",
            "name": "策略源码",
            "hidden": 2,
            "component": "strategies/code/index",
            "sort": 1,
            "meta": {
              "type": "M",
              "redirect": "",
              "icon": "IconCodeBlock",
              "activeName": "",
              "keepAlive": false,
              "defaultMenu": false,
              "title": "策略源码",
              "closeTab": false
            },
            "authoritys": null,
            "menuBtn": null,
            "level": "",
            "code": "code",
            "route": "/code",
            "redirect": "wer",
            "status": 1,
            "remark": null,
            "menuId": 4604,
            "children": null,
            "parameters": [],
            "btns": null
          },
          {
            "id": 4603,
            "CreatedAt": "2023-03-19T16:14:53.484+08:00",
            "UpdatedAt": "2023-03-19T19:38:40.431+08:00",
            "parent_id": 4606,
            "path": "/json",
            "name": "策略回测",
            "hidden": 2,
            "component": "notify/json",
            "sort": 3,
            "meta": {
              "type": "M",
              "redirect": "",
              "icon": "IconPlayArrow",
              "activeName": "",
              "keepAlive": false,
              "defaultMenu": false,
              "title": "策略回测",
              "closeTab": false
            },
            "authoritys": null,
            "menuBtn": null,
            "level": "",
            "code": "strategies",
            "route": "/strategies",
            "redirect": null,
            "status": 1,
            "remark": null,
            "menuId": 4603,
            "children": null,
            "parameters": [],
            "btns": null
          }
        ],
        "parameters": [],
        "btns": null
      }
    ],
    "user": {
      "id": 5,
      "CreatedAt": "2023-03-19T19:02:18.789+08:00",
      "UpdatedAt": "2023-03-19T19:02:18.789+08:00",
      "uuid": "da913d20-c528-4f07-aa32-7c2a730a3056",
      "userName": "genv",
      "nickName": "genv",
      "sideMode": "dark",
      "headerImg": "https://qmplusimg.henrongyi.top/gva_header.jpg",
      "baseColor": "#fff",
      "activeColor": "#1890ff",
      "authorityId": 123,
      "authority": {
        "CreatedAt": "2023-03-19T03:19:10.706+08:00",
        "UpdatedAt": "2023-03-19T23:20:51.325+08:00",
        "DeletedAt": null,
        "authorityId": 123,
        "authorityName": "机器人",
        "parentId": 0,
        "code": "bot",
        "sort": 1,
        "status": 1,
        "remark": "",
        "dataAuthorityId": null,
        "children": null,
        "menus": null,
        "defaultRouter": "404"
      },
      "authorities": [],
      "phone": "",
      "email": "",
      "enable": 1,
      "backend_setting": {
        "mode": "light",
        "tag": true,
        "menuCollapse": false,
        "menuWidth": 230,
        "layout": "columns",
        "skin": "mine",
        "i18n": false,
        "language": "zh_CN",
        "animation": "ma-slide-down",
        "color": "#165dff"
      }
    }
  },
  "msg": "获取成功"
}
